{"errors":[],"warnings":[],"namedChunkGroups":{"polyfill":{"chunks":[2,0,7],"assets":["webpack-runtime-3c4a86cf14bb81417255.js","webpack-runtime-3c4a86cf14bb81417255.js.map","commons-526002b640ba51a14497.js","commons-526002b640ba51a14497.js.map","polyfill-2a86e29ae53b0bcd324d.js","polyfill-2a86e29ae53b0bcd324d.js.map"],"children":{},"childAssets":{}},"app":{"chunks":[2,6,3],"assets":["webpack-runtime-3c4a86cf14bb81417255.js","webpack-runtime-3c4a86cf14bb81417255.js.map","framework-a576ae5ab153fa4a7c27.js","framework-a576ae5ab153fa4a7c27.js.map","app-e8d5678188112eb4bcc7.js","app-e8d5678188112eb4bcc7.js.map"],"children":{},"childAssets":{}},"component---src-pages-404-js":{"chunks":[1,0,4],"assets":["styles.d14e0792b07ae2762eb2.css","styles-c2fe8482057191dca484.js","styles-c2fe8482057191dca484.js.map","commons-526002b640ba51a14497.js","commons-526002b640ba51a14497.js.map","component---src-pages-404-js-e1a063089cb3395334da.js","component---src-pages-404-js-e1a063089cb3395334da.js.map"],"children":{},"childAssets":{}},"component---src-pages-index-js":{"chunks":[1,0,5],"assets":["styles.d14e0792b07ae2762eb2.css","styles-c2fe8482057191dca484.js","styles-c2fe8482057191dca484.js.map","commons-526002b640ba51a14497.js","commons-526002b640ba51a14497.js.map","component---src-pages-index-js-8f030b08df8d72529e75.js","component---src-pages-index-js-8f030b08df8d72529e75.js.map"],"children":{},"childAssets":{}}},"assetsByChunkName":{"polyfill":["webpack-runtime-3c4a86cf14bb81417255.js","commons-526002b640ba51a14497.js","polyfill-2a86e29ae53b0bcd324d.js"],"app":["webpack-runtime-3c4a86cf14bb81417255.js","framework-a576ae5ab153fa4a7c27.js","app-e8d5678188112eb4bcc7.js"],"component---src-pages-404-js":["styles.d14e0792b07ae2762eb2.css","styles-c2fe8482057191dca484.js","commons-526002b640ba51a14497.js","component---src-pages-404-js-e1a063089cb3395334da.js"],"component---src-pages-index-js":["styles.d14e0792b07ae2762eb2.css","styles-c2fe8482057191dca484.js","commons-526002b640ba51a14497.js","component---src-pages-index-js-8f030b08df8d72529e75.js"]}}